feedly/__init__.py
feedly/admin.py
feedly/core.py
feedly/feed.py
feedly/forms.py
feedly/hooks.py
feedly/models.py
feedly/payments.py
feedly/tests.py
feedly/urls.py
feedly/views.py
feedly/migrations/0001_initial.py
feedly/migrations/__init__.py
django_feedly-0.6.8.dist-info/LICENSE
django_feedly-0.6.8.dist-info/METADATA
django_feedly-0.6.8.dist-info/WHEEL
django_feedly-0.6.8.dist-info/top_level.txt
django_feedly-0.6.8.dist-info/RECORD
