Metadata-Version: 2.1
Name: django-feedly
Version: 0.6.8
Summary: A Django app to create list and grid-based feeds.
Home-page: https://williamlagos.github.io/
Author: William Oliveira de Lagos
Author-email: william.lagos@icloud.com
License: LGPLv3 License
Platform: UNKNOWN
Classifier: Environment :: Web Environment
Classifier: Framework :: Django
Classifier: Intended Audience :: Developers
Classifier: License :: OSI Approved :: BSD License
Classifier: Operating System :: OS Independent
Classifier: Programming Language :: Python
Classifier: Programming Language :: Python :: 2
Classifier: Programming Language :: Python :: 2.7
Classifier: Topic :: Internet :: WWW/HTTP
Classifier: Topic :: Internet :: WWW/HTTP :: Dynamic Content
